conson/__init__.py
conson/conson.py
conson-3.2.1.dist-info/LICENSE.md
conson-3.2.1.dist-info/METADATA
conson-3.2.1.dist-info/WHEEL
conson-3.2.1.dist-info/top_level.txt
conson-3.2.1.dist-info/RECORD
