Metadata-Version: 2.1
Name: conson
Version: 3.2.1
Summary: A simple json configuration file manager
Author: Paweł Gabryś
Author-email: p.gabrys@int.pl
License-File: LICENSE.md
Requires-Dist: cryptography >=41.0.3
